{
  "greet": "Hi, I’m Daiki. Nice to meet you.",
  "aboutMe": "My journey as a software engineer has started from 2016, mainly I worked for banking internal systems. I'm quietly confident, naturally curious, and perpetually working on improving my skills. Furthermore, I like to make complicated problems simple and can find and solve them quickly so I'm sure I can be help a lot for your project!",
  "sns": [
    {
      "name": "github",
      "url": "https://github.com/DaiSugi01"
    },
    {
      "name": "linkedin",
      "url": "https://www.linkedin.com/in/daiki-sugihara-97b7b7150/"
    }
  ]
}
